treehfd/__init__.py
treehfd/cartesian_partition.py
treehfd/ensemble.py
treehfd/optimization_matrix.py
treehfd/tree.py
treehfd/tree_structure.py
treehfd/validation.py
treehfd-1.1.0.dist-info/licenses/LICENSE
treehfd-1.1.0.dist-info/METADATA
treehfd-1.1.0.dist-info/WHEEL
treehfd-1.1.0.dist-info/top_level.txt
treehfd-1.1.0.dist-info/RECORD
