Metadata-Version: 2.4
Name: treehfd
Version: 1.1.0
Summary: A python module to explain xgboost models with the Hoeffding functional decomposition.
Author-email: Clement Benard <clement-l.benard@thalesgroup.com>
License: Apache-2.0
Project-URL: documentation, https://treehfd.readthedocs.io/en/latest/
Project-URL: repository, https://github.com/ThalesGroup/treehfd
Keywords: machine learning,gradient boosted tree,explainability,Hoeffding functional decomposition,functional ANOVA decomposition
Platform: Linux
Platform: Mac OS-X
Platform: Unix
Classifier: Intended Audience :: Science/Research
Classifier: License :: OSI Approved :: Apache Software License
Classifier: Operating System :: MacOS
Classifier: Operating System :: POSIX
Classifier: Programming Language :: Python :: 3.11
Classifier: Programming Language :: Python :: 3.12
Classifier: Programming Language :: Python :: 3.13
Classifier: Programming Language :: Python :: 3.14
Classifier: Topic :: Scientific/Engineering
Classifier: Topic :: Scientific/Engineering :: Artificial Intelligence
Classifier: Topic :: Scientific/Engineering :: Mathematics
Requires-Python: >=3.11
License-File: LICENSE
Requires-Dist: numpy>=2.3
Requires-Dist: xgboost>=3.1
Requires-Dist: scipy>=1.16
Requires-Dist: scikit-learn>=1.7
Requires-Dist: pandas>=2.3
Requires-Dist: tqdm>=4.67
Provides-Extra: examples
Requires-Dist: matplotlib; extra == "examples"
Provides-Extra: doc
Requires-Dist: sphinx; extra == "doc"
Requires-Dist: sphinx-rtd-theme; extra == "doc"
Provides-Extra: dev
Requires-Dist: pytest; extra == "dev"
Requires-Dist: ruff; extra == "dev"
Requires-Dist: pyright[nodejs]; extra == "dev"
Requires-Dist: coverage; extra == "dev"
Dynamic: license-file
